Metadata-Version: 1.1
Name: awsudo
Version: 0.2.0
Summary: Get temporary credentials for AWS roles.
Home-page: https://github.com/pmuller/awsudo
Author: Philippe Muller
Author-email: philippe.muller@gmail.com
License: Apache License 2.0
Platform: UNKNOWN
Classifier: Development Status :: 3 - Alpha
Classifier: Intended Audience :: System Administrators
Classifier: Intended Audience :: Developers
Classifier: Programming Language :: Python :: 2.7
Classifier: Programming Language :: Python :: 3.5
